<pkgref spec="1.12" uuid="B0332658-1065-4E22-9344-7F8CC3B5C2EE"><config><identifier>org.jamoma.modular.jamoma.Textmate.pkg</identifier><version>1.0</version><description></description><post-install type="none"/><requireAuthorization/><installFrom relative="true" mod="true">../../Installers/temp/distro/Library</installFrom><installTo mod="true">/Library/</installTo><flags><followSymbolicLinks/></flags><packageStore type="internal"></packageStore><mod>installTo</mod><mod>postInstall</mod><mod>installFrom.path</mod><mod>identifier</mod><mod>parent</mod><mod>version</mod><mod>installTo.path</mod><mod>requireAuthorization</mod><mod>extraFiles</mod></config><contents><file-list>07library-contents.xml</file-list><filter>/CVS$</filter><filter>/\.svn$</filter><filter>/\.cvsignore$</filter><filter>/\.cvspass$</filter><filter>/\.DS_Store$</filter></contents><extra-files/></pkgref>