<?xml version='1.0' encoding='iso-8859-1' standalone='yes' ?>

<jamoma version='0.6'
		xmlns:xsi='http://www.w3.org/2001/XMLSchema-instance'
		xsi:schemaLocation='http://jamoma.org/ file:jamoma.xsd'
>
  <preset name='default'>
    <command address="bypass' type='boolean">0</command>
    <command address="fade' type='decimal">0.350000</command>
    <command address="freeze' type='boolean">0</command>
    <command address="mute' type='boolean">0</command>
    <command address="noise/granularity.x' type='integer">5</command>
    <command address="noise/granularity.y' type='integer">5</command>
    <command address="noise/probability' type='decimal">0.100000</command>
    <command address="preview' type='boolean">0</command>
    <command address="stability' type='integer">100</command>
    <command address="updaterate' type='integer">33</command>
    <command address="view/freeze' type='boolean">0</command>

  </preset>
</jamoma>
